[
    {
        "_id": "reasoning-number-series",
        "subject_id": "reasoning",
        "topic": "Number Series",
        "title": "Number Series and Patterns",
        "content": "# Number Series and Patterns\n\n## Introduction\nNumber series problems require identifying patterns in sequences of numbers.\n\n## Types of Series\n\n### 1. Arithmetic Series\nConstant difference between consecutive terms.\n\n**Examples:**\n- 2, 5, 8, 11, 14, **17** (difference = +3)\n- 50, 45, 40, 35, **30** (difference = -5)\n\n### 2. Geometric Series\nConstant ratio between consecutive terms.\n\n**Examples:**\n- 2, 6, 18, 54, **162** (ratio = ×3)\n- 256, 64, 16, 4, **1** (ratio = ÷4)\n\n### 3. Square Series\nInvolves perfect squares.\n\n**Examples:**\n- 1, 4, 9, 16, 25, **36** (n²)\n- 2, 5, 10, 17, 26, **37** (n² + 1)\n\n### 4. Cube Series\nInvolves perfect cubes.\n\n**Examples:**\n- 1, 8, 27, 64, **125** (n³)\n- 2, 9, 28, 65, **126** (n³ + 1)\n\n### 5. Fibonacci Series\nEach term = sum of two preceding terms.\n\n**Example:**\n- 1, 1, 2, 3, 5, 8, 13, **21**, **34**\n\n### 6. Prime Number Series\n- 2, 3, 5, 7, 11, 13, **17**, **19**\n\n### 7. Increasing Difference Series\nDifference increases progressively.\n\n**Examples:**\n- 1, 2, 4, 7, 11, **16** (diff: +1, +2, +3, +4, +5)\n- 2, 3, 5, 8, 12, **17** (diff: +1, +2, +3, +4, +5)\n\n### 8. Alternating Series\nTwo patterns alternate.\n\n**Example:**\n- 1, 2, 2, 4, 3, 6, 4, **8** (Odd positions: +1, Even positions: +2)\n\n## Problem Solving Strategy\n\n### Step 1: Find Differences\nCalculate difference between consecutive terms.\n\n### Step 2: Check Pattern\n- If differences are constant → Arithmetic\n- If differences form a pattern → Check for squares, cubes\n- If ratios are constant → Geometric\n\n### Step 3: Apply Pattern\nExtend the pattern to find the answer.\n\n## Practice Problems\n\n**Q1:** 3, 6, 11, 18, 27, ?\n- Differences: 3, 5, 7, 9, **11**\n- Answer: 27 + 11 = **38**\n\n**Q2:** 2, 6, 12, 20, 30, ?\n- Pattern: n(n+1) → 1×2, 2×3, 3×4, 4×5, 5×6\n- Answer: 6×7 = **42**\n\n**Q3:** 1, 4, 27, 256, ?\n- Pattern: 1¹, 2², 3³, 4⁴\n- Answer: 5⁵ = **3125**\n\n**Q4:** 5, 11, 23, 47, ?\n- Pattern: ×2 + 1\n- Answer: 47×2 + 1 = **95**\n\n**Q5:** 7, 10, 8, 11, 9, 12, ?\n- Pattern: +3, -2, +3, -2, +3, -2\n- Answer: 12 - 2 = **10**\n\n## Tips\n1. Always calculate differences first\n2. Look for squares and cubes\n3. Check for alternating patterns\n4. Consider multiplication patterns\n5. Prime numbers may be involved",
        "exam_tags": ["ssc", "banking", "railway", "upsc"]
    },
    {
        "_id": "reasoning-coding-decoding",
        "subject_id": "reasoning",
        "topic": "Coding-Decoding",
        "title": "Coding and Decoding",
        "content": "# Coding and Decoding\n\n## Introduction\nIn coding-decoding, letters/words are coded using a specific pattern. You need to identify the pattern and decode or encode.\n\n## Types of Coding\n\n### 1. Letter Shifting\nEach letter is shifted by a fixed number.\n\n**Example:**\nIf CAT = DBU (each letter +1)\nThen DOG = **EPH**\n\n### Alphabet Position Reference\nA=1, B=2, C=3... Z=26\n\n### 2. Reverse Alphabet Coding\nA↔Z, B↔Y, C↔X, etc.\n\n| Original | A | B | C | D | ... | W | X | Y | Z |\n|----------|---|---|---|---|-----|---|---|---|---|\n| Coded | Z | Y | X | W | ... | D | C | B | A |\n\n**Example:**\nCODE = XLWV\n\n### 3. Number Coding\nLetters replaced by their position numbers.\n\n**Example:**\nCAT = 3-1-20\nBAD = 2-1-4\n\n### 4. Symbol/Pattern Coding\nLetters represented by symbols.\n\n**Example:**\nIf ROAD = @#$%, then DOOR = %##@\n\n### 5. Word Substitution\nWords are replaced by other words.\n\n**Example:**\nIf 'sky' means 'sea', 'sea' means 'tree', 'tree' means 'road'\nThen \"Birds fly in the sky\" = \"Birds fly in the **sea**\"\n\n## Coding Patterns\n\n### Pattern 1: +1 Shift\n| Original | Coded |\n|----------|-------|\n| A | B |\n| B | C |\n| C | D |\n\n### Pattern 2: -1 Shift\n| Original | Coded |\n|----------|-------|\n| A | Z |\n| B | A |\n| C | B |\n\n### Pattern 3: +2 Shift\n| Original | Coded |\n|----------|-------|\n| A | C |\n| B | D |\n| C | E |\n\n### Pattern 4: Opposite Letters\n| Original | Coded |\n|----------|-------|\n| A (1) | Z (26) |\n| B (2) | Y (25) |\n| C (3) | X (24) |\n\nFormula: Coded = 27 - Position\n\n## Practice Problems\n\n**Q1:** If COMPUTER = RFUVQNPC, then PRINTER = ?\n- Pattern: Reverse order\n- Answer: **RETNIRP**\n\n**Q2:** If CAT = 24, then BAT = ?\n- C=3, A=1, T=20 → 3+1+20=24\n- B=2, A=1, T=20 → 2+1+20=**23**\n\n**Q3:** If ROAD = URDG, then SWAN = ?\n- Pattern: R(+3)=U, O(+3)=R, A(+3)=D, D(+3)=G\n- S(+3)=V, W(+3)=Z, A(+3)=D, N(+3)=Q\n- Answer: **VZDQ**\n\n**Q4:** In a code, FIRE is written as DGPC. How is WATER written?\n- Pattern: -2 for each letter\n- W(-2)=U, A(-2)=Y (Z→A wrap), T(-2)=R, E(-2)=C, R(-2)=P\n- Answer: **UYRCR** or check pattern carefully\n\n## Tips\n1. Write alphabet with positions\n2. Identify the shift pattern first\n3. Check if it's same shift or variable\n4. Consider reverse alphabet coding\n5. Check for word-level operations",
        "exam_tags": ["ssc", "banking", "railway", "upsc"]
    }
]
